composed_trackers/__init__.py
composed_trackers/composer.py
composed_trackers/version.py
composed_trackers/loggers/__init__.py
composed_trackers/loggers/base.py
composed_trackers/loggers/neptune.py
composed_trackers/loggers/simple.py
composed_trackers/utils/__init__.py
composed_trackers/utils/log.py
composed_trackers/utils/utils.py
composed_trackers/utils/streams/__init__.py
composed_trackers/utils/streams/stdstream.py
composed_trackers-0.0.2.dist-info/LICENSE
composed_trackers-0.0.2.dist-info/METADATA
composed_trackers-0.0.2.dist-info/WHEEL
composed_trackers-0.0.2.dist-info/top_level.txt
composed_trackers-0.0.2.dist-info/RECORD
