Metadata-Version: 2.1
Name: composed-trackers
Version: 0.0.2
Summary: Trackres adapters and interfaces
Home-page: https://github.com/goodok/composed-trackers
Author: Alexey U. Gudchenko
Author-email: proga@goodok.ru
License: UNKNOWN
Platform: UNKNOWN
Requires-Python: >=3.6
Requires-Dist: torch (>=1.0.0)
Requires-Dist: trimesh
Requires-Dist: humanize
Requires-Dist: ipyvolume
Requires-Dist: pythreejs
Requires-Dist: joblib
Requires-Dist: autopep8
Requires-Dist: jupyter
Requires-Dist: jupyter-contrib-nbextensions
Requires-Dist: PyChromeDevTools
Requires-Dist: matplotlib
Requires-Dist: pandas
Requires-Dist: tqdm
Requires-Dist: dataclasses
Requires-Dist: neptune-client
Requires-Dist: fastai-sparse
Requires-Dist: kekas (>=0.1.23)
Requires-Dist: seaborn
Requires-Dist: plotly
Requires-Dist: albumentations
Requires-Dist: mmcv
Requires-Dist: mmdet
Provides-Extra: dev
Requires-Dist: coverage ; extra == 'dev'
Requires-Dist: distro ; extra == 'dev'
Requires-Dist: ipython ; extra == 'dev'
Requires-Dist: jupyter ; extra == 'dev'
Requires-Dist: jupyter-contrib-nbextensions ; extra == 'dev'
Requires-Dist: nbconvert (>=5.4) ; extra == 'dev'
Requires-Dist: nbdime ; extra == 'dev'
Requires-Dist: nbformat ; extra == 'dev'
Requires-Dist: notebook (>=5.7.0) ; extra == 'dev'
Requires-Dist: pip (>=9.0.1) ; extra == 'dev'
Requires-Dist: pipreqs (>=0.4.9) ; extra == 'dev'
Requires-Dist: pytest ; extra == 'dev'
Requires-Dist: pytest-xdist ; extra == 'dev'
Requires-Dist: responses ; extra == 'dev'
Requires-Dist: traitlets ; extra == 'dev'
Requires-Dist: wheel (>=0.30.0) ; extra == 'dev'
Requires-Dist: graphviz ; extra == 'dev'
